[
  {
    "id": "P031",
    "nev": "P031",
    "kapacitas_osszes": null,
    "szabad_helyek": null,
    "foglalt_helyek": 6,
    "latitude": null,
    "longitude": null,
    "meres_ideje": "2026-04-05T13:57:31+02:00",
    "lekerdezes_ideje": "2026-04-05T12:00:55"
  },
  {
    "id": "P051",
    "nev": "P051",
    "kapacitas_osszes": null,
    "szabad_helyek": null,
    "foglalt_helyek": 36,
    "latitude": null,
    "longitude": null,
    "meres_ideje": "2026-04-05T13:57:31+02:00",
    "lekerdezes_ideje": "2026-04-05T12:00:55"
  },
  {
    "id": "P061",
    "nev": "P061",
    "kapacitas_osszes": null,
    "szabad_helyek": null,
    "foglalt_helyek": 59,
    "latitude": null,
    "longitude": null,
    "meres_ideje": "2026-04-05T13:57:31+02:00",
    "lekerdezes_ideje": "2026-04-05T12:00:55"
  },
  {
    "id": "P071",
    "nev": "P071",
    "kapacitas_osszes": null,
    "szabad_helyek": null,
    "foglalt_helyek": 39,
    "latitude": null,
    "longitude": null,
    "meres_ideje": "2026-04-05T13:51:20+02:00",
    "lekerdezes_ideje": "2026-04-05T12:00:55"
  },
  {
    "id": "P101",
    "nev": "P101",
    "kapacitas_osszes": null,
    "szabad_helyek": null,
    "foglalt_helyek": 69,
    "latitude": null,
    "longitude": null,
    "meres_ideje": "2026-04-05T13:57:31+02:00",
    "lekerdezes_ideje": "2026-04-05T12:00:55"
  },
  {
    "id": "P111",
    "nev": "P111",
    "kapacitas_osszes": null,
    "szabad_helyek": null,
    "foglalt_helyek": 43,
    "latitude": null,
    "longitude": null,
    "meres_ideje": "2026-04-05T13:57:31+02:00",
    "lekerdezes_ideje": "2026-04-05T12:00:55"
  },
  {
    "id": "P121",
    "nev": "P121",
    "kapacitas_osszes": null,
    "szabad_helyek": null,
    "foglalt_helyek": 115,
    "latitude": null,
    "longitude": null,
    "meres_ideje": "2026-04-05T13:57:31+02:00",
    "lekerdezes_ideje": "2026-04-05T12:00:55"
  },
  {
    "id": "P131",
    "nev": "P131",
    "kapacitas_osszes": null,
    "szabad_helyek": null,
    "foglalt_helyek": 115,
    "latitude": null,
    "longitude": null,
    "meres_ideje": "2026-04-05T13:57:31+02:00",
    "lekerdezes_ideje": "2026-04-05T12:00:55"
  },
  {
    "id": "P141",
    "nev": "P141",
    "kapacitas_osszes": null,
    "szabad_helyek": null,
    "foglalt_helyek": 1,
    "latitude": null,
    "longitude": null,
    "meres_ideje": "2026-04-05T13:57:31+02:00",
    "lekerdezes_ideje": "2026-04-05T12:00:55"
  },
  {
    "id": "P151",
    "nev": "P151",
    "kapacitas_osszes": null,
    "szabad_helyek": null,
    "foglalt_helyek": 21,
    "latitude": null,
    "longitude": null,
    "meres_ideje": "2026-04-05T13:57:31+02:00",
    "lekerdezes_ideje": "2026-04-05T12:00:55"
  },
  {
    "id": "P171",
    "nev": "P171",
    "kapacitas_osszes": null,
    "szabad_helyek": null,
    "foglalt_helyek": 278,
    "latitude": null,
    "longitude": null,
    "meres_ideje": "2026-04-05T13:55:59+02:00",
    "lekerdezes_ideje": "2026-04-05T12:00:55"
  },
  {
    "id": "P191",
    "nev": "P191",
    "kapacitas_osszes": null,
    "szabad_helyek": null,
    "foglalt_helyek": 61,
    "latitude": null,
    "longitude": null,
    "meres_ideje": "2026-04-05T13:57:31+02:00",
    "lekerdezes_ideje": "2026-04-05T12:00:55"
  },
  {
    "id": "P201",
    "nev": "P201",
    "kapacitas_osszes": null,
    "szabad_helyek": null,
    "foglalt_helyek": 73,
    "latitude": null,
    "longitude": null,
    "meres_ideje": "2026-04-05T13:58:02+02:00",
    "lekerdezes_ideje": "2026-04-05T12:00:55"
  },
  {
    "id": "P211",
    "nev": "P211",
    "kapacitas_osszes": null,
    "szabad_helyek": null,
    "foglalt_helyek": 97,
    "latitude": null,
    "longitude": null,
    "meres_ideje": "2026-04-05T13:52:53+02:00",
    "lekerdezes_ideje": "2026-04-05T12:00:55"
  },
  {
    "id": "P221",
    "nev": "P221",
    "kapacitas_osszes": null,
    "szabad_helyek": null,
    "foglalt_helyek": 142,
    "latitude": null,
    "longitude": null,
    "meres_ideje": "2026-04-05T13:51:51+02:00",
    "lekerdezes_ideje": "2026-04-05T12:00:55"
  },
  {
    "id": "P251",
    "nev": "P251",
    "kapacitas_osszes": null,
    "szabad_helyek": null,
    "foglalt_helyek": 475,
    "latitude": null,
    "longitude": null,
    "meres_ideje": "2026-04-05T13:53:24+02:00",
    "lekerdezes_ideje": "2026-04-05T12:00:55"
  }
]